prolog_code_generator/CodeGenerator.py
prolog_code_generator/__init__.py
prolog_code_generator/excel_template.py
Prolog_Code_Generator-1.0.0.dist-info/METADATA
Prolog_Code_Generator-1.0.0.dist-info/WHEEL
Prolog_Code_Generator-1.0.0.dist-info/top_level.txt
Prolog_Code_Generator-1.0.0.dist-info/RECORD
