Metadata-Version: 2.1
Name: Prolog-Code-Generator
Version: 1.0.0
Summary: expert system code generator
Home-page: https://github.com/ShootGan/prolog-code-generator
Author: Pawel Nalepka
Author-email: nawelpalepka@gmail.com
Project-URL: Bug Tracker, https://github.com/ShootGan/prolog-code-generator/issues
Classifier: Programming Language :: Python :: 3
Classifier: License :: OSI Approved :: MIT License
Classifier: Operating System :: OS Independent
Requires-Python: >=3.6
